Workbook
Name aporte: Planilha1!$D$15
Name aporte_perfil: Planilha1!$C$30
Name dividendos: Planilha1!$D$19
Name patrimonio: Planilha1!$D$18
Name Perfil: Planilha1!$C$29
Name Rendim_carteira: Planilha1!$D$11
Name salario: Planilha1!$D$10
Name sugestao_investimento: Planilha1!$D$12
Name taxa_mensal: Planilha1!$D$17
Name tempo_invest: Planilha1!$D$16

Sheet Planilha1
B9: C O N F I G U R A Ç Õ E S
B10: Salário | D10: 4200
B11: Rendimento Carteira | D11: 0.007
B12: Sugestão Investimento 30% | D12: =D10*0.3 -> 1260
B14: I N V E S T I M E N T O M E N S A L
B15: Quanto investir por mês | D15: 1260
B16: Por quantos anos | D16: 5
B17: Taxa Rendimento Mensal | D17: 0.01079
B18: Quanto de Patrimônio Acumulado | D18: =FV(taxa_mensal,tempo_invest*12,aporte*-1) -> 105558.91
B19: Quanto de Dividendos por Mês | D19: =patrimonio*Rendim_carteira -> 738.91238
B22: Cenários | D22: dividendos
A23: 2 | B23: Quanto em 2 anos? | C23: =FV($D$17,$A23*12,$D$15*-1) -> 34306.81 | D23: =C23*Rendim_carteira -> 240.14767
A24: 5 | B24: Quanto em 5 anos? | C24: =FV($D$17,$A24*12,$D$15*-1) -> 105558.91 | D24: =C24*Rendim_carteira -> 738.91238
A25: 10 | B25: Quanto em 10 anos? | C25: =FV($D$17,$A25*12,$D$15*-1) -> 306538.11 | D25: =C25*Rendim_carteira -> 2145.7668
A26: 20 | B26: Quanto em 20 anos? | C26: =FV($D$17,$A26*12,$D$15*-1) -> 1417750 | D26: =C26*Rendim_carteira -> 9924.2499
A27: 30 | B27: Quanto em 30 anos? | C27: =FV($D$17,$A27*12,$D$15*-1) -> 5445933.8 | D27: =C27*Rendim_carteira -> 38121.536
B29: PERFIL | C29: Conservador
B30: VALOR A SER INVESTIDO POR MÊS | C30: =aporte -> 1260
B33: ="O PERFIL SELECIONADO É O:"&" "&Perfil -> O PERFIL SELECIONADO É O: Conservador
B34: TIPOS DE FII | C34: Percentual Sugerido | D34: Valores
B35: PAPEL | C35: =VLOOKUP(Perfil&"-"&B35,Planilha2!C:F,4,FALSE) -> 0.3 | D35: =C35*aporte_perfil -> 378
B36: TIJOLO | C36: =VLOOKUP(Perfil&"-"&B36,Planilha2!C:F,4,FALSE) -> 0.5 | D36: =C36*aporte_perfil -> 630
B37: HIBRIDOS | C37: =VLOOKUP(Perfil&"-"&B37,Planilha2!C:F,4,FALSE) -> 0.1 | D37: =C37*aporte_perfil -> 126
B38: FOFs | C38: =VLOOKUP(Perfil&"-"&B38,Planilha2!C:F,4,FALSE) -> 0.1 | D38: =C38*aporte_perfil -> 126
B39: DESENVOLVIMENTO | C39: =VLOOKUP(Perfil&"-"&B39,Planilha2!C:F,4,FALSE) -> 0 | D39: =C39*aporte_perfil -> 0
B40: HOTELARIAS | C40: =VLOOKUP(Perfil&"-"&B40,Planilha2!C:F,4,FALSE) -> 0 | D40: =C40*aporte_perfil -> 0
D41: =SUM(D35:D40) -> 1260

Sheet Planilha2
C3: CHAVE | D3: PERFIL | E3: TIPOS DE FII | F3: Percentual Sugerido
C4: =D4&"-"&E4 -> Conservador-PAPEL | D4: Conservador | E4: PAPEL | F4: 0.3
C5: =D5&"-"&E5 -> Conservador-TIJOLO | D5: Conservador | E5: TIJOLO | F5: 0.5
C6: =D6&"-"&E6 -> Conservador-HIBRIDOS | D6: Conservador | E6: HIBRIDOS | F6: 0.1
C7: =D7&"-"&E7 -> Conservador-FOFs | D7: Conservador | E7: FOFs | F7: 0.1
C8: =D8&"-"&E8 -> Conservador-DESENVOLVIMENTO | D8: Conservador | E8: DESENVOLVIMENTO | F8: 0
C9: =D9&"-"&E9 -> Conservador-HOTELARIAS | D9: Conservador | E9: HOTELARIAS | F9: 0
C10: =D10&"-"&E10 -> Moderado-PAPEL | D10: Moderado | E10: PAPEL | F10: 0.32
C11: =D11&"-"&E11 -> Moderado-TIJOLO | D11: Moderado | E11: TIJOLO | F11: 0.4
C12: =D12&"-"&E12 -> Moderado-HIBRIDOS | D12: Moderado | E12: HIBRIDOS | F12: 0.08
C13: =D13&"-"&E13 -> Moderado-FOFs | D13: Moderado | E13: FOFs | F13: 0.1
C14: =D14&"-"&E14 -> Moderado-DESENVOLVIMENTO | D14: Moderado | E14: DESENVOLVIMENTO | F14: 0.1
C15: =D15&"-"&E15 -> Moderado-HOTELARIAS | D15: Moderado | E15: HOTELARIAS | F15: 0
... C21: =D21&"-"&E21 -> Agressivo-HOTELARIAS | D21: Agressivo | E21: HOTELARIAS | F21: 0.1
